{
  "001": {
    "name": "Baker County",
    "fips": "OR",
    "pop10": "16134",
    "lat": 44.703427,
    "lon": -117.691933,
    "geoid": "41001",
    "deaths": 2,
    "prop_dmg": "10.0k",
    "crop_dmg": "10.0k",
    "inj": 2,
    "all": 2,
    "eq": [],
    "Hurricane____Typhoon___": [],
    "Cold__FWind_Chill": [],
    "Coastal_Flood": [],
    "Avalanche": [
      {
        "type": "Avalanche",
        "time": "1300",
        "inj": "2",
        "deaths": "2",
        "prop_dmg": "0",
        "crop_dmg": "0",
        "begin": "02/11/2014",
        "county": "BAKER ",
        "state": "OR"
      }
    ],
    "Astronomical_Low_Tide": [],
    "Dense_Fog": [],
    "Drought": [],
    "Dust_Devil": [],
    "Dust_Storm": [],
    "Excessive_Heat": [],
    "Extreme_Cold__FWind_Chill": [],
    "Flash_Flood": [],
    "Flood": [
      {
        "type": "Flood",
        "time": "2300",
        "inj": "0",
        "deaths": "0",
        "prop_dmg": "10.0k",
        "crop_dmg": "10.0k",
        "begin": "06/02/2010",
        "county": "BAKER CO.",
        "state": "OR"
      }
    ],
    "Freezing_Fog": [],
    "Funnel_Cloud": [],
    "Hail": [],
    "Heat": [],
    "Heavy_Rain": [],
    "Heavy_Snow": [],
    "High_Surf": [],
    "High_Wind": [],
    "Ice_Storm": [],
    "Lakeshore_Flood": [],
    "Landslide": [],
    "Lightning": [],
    "Rip_Current": [],
    "Seiche": [],
    "Sleet": [],
    "Storm_Surge__FTide": [],
    "Strong_Wind": [],
    "Thunderstorm_Wind": [],
    "Tornado": [],
    "Tropical_Depression": [],
    "Tropical_Storm": [],
    "Tsunami": [],
    "Volcanic_Ashfall": [],
    "Waterspout": [],
    "Wildfire": [],
    "Winter_Storm": [],
    "Winter_Weather": []
  },
  "003": {
    "name": "Benton County",
    "fips": "OR",
    "pop10": "85579",
    "lat": 44.490623,
    "lon": -123.426317,
    "geoid": "41003",
    "deaths": 2,
    "prop_dmg": "4.12M",
    "crop_dmg": 0,
    "inj": 0,
    "all": 6,
    "eq": [],
    "Hurricane____Typhoon___": [],
    "Cold__FWind_Chill": [],
    "Coastal_Flood": [],
    "Avalanche": [],
    "Astronomical_Low_Tide": [],
    "Dense_Fog": [],
    "Drought": [],
    "Dust_Devil": [],
    "Dust_Storm": [],
    "Excessive_Heat": [],
    "Extreme_Cold__FWind_Chill": [],
    "Flash_Flood": [],
    "Flood": [
      {
        "type": "Flood",
        "time": "1100",
        "inj": "0",
        "deaths": "0",
        "prop_dmg": "3.00M",
        "crop_dmg": "0",
        "begin": "01/18/2012",
        "county": "BENTON CO.",
        "state": "OR"
      }
    ],
    "Freezing_Fog": [],
    "Funnel_Cloud": [],
    "Hail": [],
    "Heat": [
      {
        "type": "Heat",
        "time": "0",
        "inj": "0",
        "deaths": "1",
        "prop_dmg": "0",
        "crop_dmg": "0",
        "begin": "07/26/1998",
        "county": "COLUMBIA/C & W MULTNOMAH/WASHINGTON/NW CLACKAMAS ",
        "state": "OR"
      }
    ],
    "Heavy_Rain": [],
    "Heavy_Snow": [],
    "High_Surf": [],
    "High_Wind": [],
    "Ice_Storm": [
      {
        "type": "Ice+Storm",
        "time": "0",
        "inj": "0",
        "deaths": "1",
        "prop_dmg": "1.00M",
        "crop_dmg": "0",
        "begin": "01/12/1998",
        "county": "COLUMBIA/C & W MULTNOMAH/WASHINGTON/NW CLACKAMAS ",
        "state": "OR"
      },
      {
        "type": "Ice+Storm",
        "time": "2200",
        "inj": "0",
        "deaths": "0",
        "prop_dmg": "8.00k",
        "crop_dmg": "0",
        "begin": "11/13/2014",
        "county": "CENTRAL COAST RANGE OF W OREGON ",
        "state": "OR"
      }
    ],
    "Lakeshore_Flood": [],
    "Landslide": [],
    "Lightning": [
      {
        "type": "Lightning",
        "time": "1200",
        "inj": "0",
        "deaths": "0",
        "prop_dmg": "11.0k",
        "crop_dmg": "0",
        "begin": "07/13/2014",
        "county": "BENTON CO.",
        "state": "OR"
      }
    ],
    "Rip_Current": [],
    "Seiche": [],
    "Sleet": [],
    "Storm_Surge__FTide": [],
    "Strong_Wind": [],
    "Thunderstorm_Wind": [],
    "Tornado": [],
    "Tropical_Depression": [],
    "Tropical_Storm": [],
    "Tsunami": [],
    "Volcanic_Ashfall": [],
    "Waterspout": [],
    "Wildfire": [],
    "Winter_Storm": [
      {
        "type": "Winter+Storm",
        "time": "1500",
        "inj": "0",
        "deaths": "0",
        "prop_dmg": "100k",
        "crop_dmg": "0",
        "begin": "01/10/1998",
        "county": "COLUMBIA/C & W MULTNOMAH/WASHINGTON/NW CLACKAMAS ",
        "state": "OR"
      }
    ],
    "Winter_Weather": []
  },
  "005": {
    "name": "Clackamas County",
    "fips": "OR",
    "pop10": "375992",
    "lat": 45.160493,
    "lon": -122.195127,
    "geoid": "41005",
    "deaths": 1,
    "prop_dmg": "20.3M",
    "crop_dmg": 0,
    "inj": 3,
    "all": 9,
    "eq": [
      {
        "type": "earthquake",
        "begin": "3/25/1993",
        "inj": "",
        "prop_dmg": "",
        "crop_dmg": "",
        "county": "WASHINGTON-OREGON BORDER",
        "state": "WA",
        "deaths": ""
      }
    ],
    "Hurricane____Typhoon___": [],
    "Cold__FWind_Chill": [],
    "Coastal_Flood": [],
    "Avalanche": [],
    "Astronomical_Low_Tide": [],
    "Dense_Fog": [],
    "Drought": [],
    "Dust_Devil": [],
    "Dust_Storm": [],
    "Excessive_Heat": [],
    "Extreme_Cold__FWind_Chill": [],
    "Flash_Flood": [],
    "Flood": [
      {
        "type": "Flood",
        "time": "630",
        "inj": "0",
        "deaths": "1",
        "prop_dmg": "250k",
        "crop_dmg": "0",
        "begin": "01/02/2009",
        "county": "CLACKAMAS CO.",
        "state": "OR"
      },
      {
        "type": "Flood",
        "time": "1000",
        "inj": "0",
        "deaths": "0",
        "prop_dmg": "9.00M",
        "crop_dmg": "0",
        "begin": "01/16/2011",
        "county": "CLACKAMAS CO.",
        "state": "OR"
      },
      {
        "type": "Flood",
        "time": "1000",
        "inj": "0",
        "deaths": "0",
        "prop_dmg": "9.00M",
        "crop_dmg": "0",
        "begin": "01/16/2011",
        "county": "CLACKAMAS CO.",
        "state": "OR"
      },
      {
        "type": "Flood",
        "time": "600",
        "inj": "0",
        "deaths": "0",
        "prop_dmg": "1.00M",
        "crop_dmg": "0",
        "begin": "01/19/2012",
        "county": "CLACKAMAS CO.",
        "state": "OR"
      },
      {
        "type": "Flood",
        "time": "2000",
        "inj": "0",
        "deaths": "0",
        "prop_dmg": "1.00M",
        "crop_dmg": "0",
        "begin": "01/19/2012",
        "county": "CLACKAMAS CO.",
        "state": "OR"
      }
    ],
    "Freezing_Fog": [],
    "Funnel_Cloud": [],
    "Hail": [],
    "Heat": [],
    "Heavy_Rain": [
      {
        "type": "Heavy+Rain",
        "time": "500",
        "inj": "0",
        "deaths": "0",
        "prop_dmg": "75.0k",
        "crop_dmg": "0",
        "begin": "01/02/2009",
        "county": "CLACKAMAS CO.",
        "state": "OR"
      }
    ],
    "Heavy_Snow": [],
    "High_Surf": [],
    "High_Wind": [],
    "Ice_Storm": [],
    "Lakeshore_Flood": [],
    "Landslide": [],
    "Lightning": [
      {
        "type": "Lightning",
        "time": "1700",
        "inj": "1",
        "deaths": "0",
        "prop_dmg": "0",
        "crop_dmg": "0",
        "begin": "04/10/2003",
        "county": "CLACKAMAS CO.",
        "state": "OR"
      },
      {
        "type": "Lightning",
        "time": "1600",
        "inj": "2",
        "deaths": "0",
        "prop_dmg": "0",
        "crop_dmg": "0",
        "begin": "06/29/2008",
        "county": "CLACKAMAS CO.",
        "state": "OR"
      }
    ],
    "Rip_Current": [],
    "Seiche": [],
    "Sleet": [],
    "Storm_Surge__FTide": [],
    "Strong_Wind": [],
    "Thunderstorm_Wind": [],
    "Tornado": [],
    "Tropical_Depression": [],
    "Tropical_Storm": [],
    "Tsunami": [],
    "Volcanic_Ashfall": [],
    "Waterspout": [],
    "Wildfire": [],
    "Winter_Storm": [],
    "Winter_Weather": []
  },
  "007": {
    "name": "Clatsop County",
    "fips": "OR",
    "pop10": "37039",
    "lat": 46.024509,
    "lon": -123.705014,
    "geoid": "41007",
    "deaths": 0,
    "prop_dmg": 0,
    "crop_dmg": 0,
    "inj": 0,
    "all": 0,
    "eq": [],
    "Hurricane____Typhoon___": [],
    "Cold__FWind_Chill": [],
    "Coastal_Flood": [],
    "Avalanche": [],
    "Astronomical_Low_Tide": [],
    "Dense_Fog": [],
    "Drought": [],
    "Dust_Devil": [],
    "Dust_Storm": [],
    "Excessive_Heat": [],
    "Extreme_Cold__FWind_Chill": [],
    "Flash_Flood": [],
    "Flood": [],
    "Freezing_Fog": [],
    "Funnel_Cloud": [],
    "Hail": [],
    "Heat": [],
    "Heavy_Rain": [],
    "Heavy_Snow": [],
    "High_Surf": [],
    "High_Wind": [],
    "Ice_Storm": [],
    "Lakeshore_Flood": [],
    "Landslide": [],
    "Lightning": [],
    "Rip_Current": [],
    "Seiche": [],
    "Sleet": [],
    "Storm_Surge__FTide": [],
    "Strong_Wind": [],
    "Thunderstorm_Wind": [],
    "Tornado": [],
    "Tropical_Depression": [],
    "Tropical_Storm": [],
    "Tsunami": [],
    "Volcanic_Ashfall": [],
    "Waterspout": [],
    "Wildfire": [],
    "Winter_Storm": [],
    "Winter_Weather": []
  },
  "009": {
    "name": "Columbia County",
    "fips": "OR",
    "pop10": "49351",
    "lat": 45.941932,
    "lon": -123.081079,
    "geoid": "41009",
    "deaths": 0,
    "prop_dmg": "300k",
    "crop_dmg": 0,
    "inj": 0,
    "all": 2,
    "eq": [],
    "Hurricane____Typhoon___": [],
    "Cold__FWind_Chill": [],
    "Coastal_Flood": [],
    "Avalanche": [],
    "Astronomical_Low_Tide": [],
    "Dense_Fog": [],
    "Drought": [],
    "Dust_Devil": [],
    "Dust_Storm": [],
    "Excessive_Heat": [],
    "Extreme_Cold__FWind_Chill": [],
    "Flash_Flood": [],
    "Flood": [
      {
        "type": "Flood",
        "time": "0",
        "inj": "0",
        "deaths": "0",
        "prop_dmg": "200k",
        "crop_dmg": "0",
        "begin": "01/01/1997",
        "county": "LOWER COLUMBIA ",
        "state": "OR"
      }
    ],
    "Freezing_Fog": [],
    "Funnel_Cloud": [],
    "Hail": [],
    "Heat": [],
    "Heavy_Rain": [],
    "Heavy_Snow": [],
    "High_Surf": [],
    "High_Wind": [],
    "Ice_Storm": [],
    "Lakeshore_Flood": [],
    "Landslide": [],
    "Lightning": [],
    "Rip_Current": [],
    "Seiche": [],
    "Sleet": [],
    "Storm_Surge__FTide": [],
    "Strong_Wind": [],
    "Thunderstorm_Wind": [],
    "Tornado": [],
    "Tropical_Depression": [],
    "Tropical_Storm": [],
    "Tsunami": [],
    "Volcanic_Ashfall": [],
    "Waterspout": [],
    "Wildfire": [],
    "Winter_Storm": [
      {
        "type": "Winter+Storm",
        "time": "1900",
        "inj": "0",
        "deaths": "0",
        "prop_dmg": "100k",
        "crop_dmg": "0",
        "begin": "01/10/1998",
        "county": "YAMHILL/POLK/C & W MARION/SW CLACKAMAS ",
        "state": "OR"
      }
    ],
    "Winter_Weather": []
  },
  "011": {
    "name": "Coos County",
    "fips": "OR",
    "pop10": "63043",
    "lat": 43.184193,
    "lon": -124.092557,
    "geoid": "41011",
    "deaths": 5,
    "prop_dmg": "1.00M",
    "crop_dmg": 0,
    "inj": 1,
    "all": 4,
    "eq": [],
    "Hurricane____Typhoon___": [],
    "Cold__FWind_Chill": [],
    "Coastal_Flood": [],
    "Avalanche": [],
    "Astronomical_Low_Tide": [],
    "Dense_Fog": [],
    "Drought": [],
    "Dust_Devil": [],
    "Dust_Storm": [],
    "Excessive_Heat": [],
    "Extreme_Cold__FWind_Chill": [],
    "Flash_Flood": [],
    "Flood": [],
    "Freezing_Fog": [],
    "Funnel_Cloud": [],
    "Hail": [],
    "Heat": [],
    "Heavy_Rain": [],
    "Heavy_Snow": [],
    "High_Surf": [
      {
        "type": "High+Surf",
        "time": "2040",
        "inj": "0",
        "deaths": "0",
        "prop_dmg": "1.00M",
        "crop_dmg": "0",
        "begin": "09/19/2005",
        "county": "SOUTH CENTRAL OREGON COAST ",
        "state": "OR"
      },
      {
        "type": "High+Surf",
        "time": "600",
        "inj": "0",
        "deaths": "3",
        "prop_dmg": "0",
        "crop_dmg": "0",
        "begin": "05/09/2006",
        "county": "SOUTH CENTRAL OREGON COAST ",
        "state": "OR"
      },
      {
        "type": "High+Surf",
        "time": "1430",
        "inj": "0",
        "deaths": "2",
        "prop_dmg": "0",
        "crop_dmg": "0",
        "begin": "10/25/2008",
        "county": "SOUTH CENTRAL OREGON COAST ",
        "state": "OR"
      }
    ],
    "High_Wind": [],
    "Ice_Storm": [],
    "Lakeshore_Flood": [],
    "Landslide": [],
    "Lightning": [
      {
        "type": "Lightning",
        "time": "1200",
        "inj": "1",
        "deaths": "0",
        "prop_dmg": "0",
        "crop_dmg": "0",
        "begin": "09/05/2013",
        "county": "COOS CO.",
        "state": "OR"
      }
    ],
    "Rip_Current": [],
    "Seiche": [],
    "Sleet": [],
    "Storm_Surge__FTide": [],
    "Strong_Wind": [],
    "Thunderstorm_Wind": [],
    "Tornado": [],
    "Tropical_Depression": [],
    "Tropical_Storm": [],
    "Tsunami": [],
    "Volcanic_Ashfall": [],
    "Waterspout": [],
    "Wildfire": [],
    "Winter_Storm": [],
    "Winter_Weather": []
  },
  "013": {
    "name": "Crook County",
    "fips": "OR",
    "pop10": "20978",
    "lat": 44.163054,
    "lon": -120.371585,
    "geoid": "41013",
    "deaths": 0,
    "prop_dmg": 0,
    "crop_dmg": 0,
    "inj": 0,
    "all": 0,
    "eq": [],
    "Hurricane____Typhoon___": [],
    "Cold__FWind_Chill": [],
    "Coastal_Flood": [],
    "Avalanche": [],
    "Astronomical_Low_Tide": [],
    "Dense_Fog": [],
    "Drought": [],
    "Dust_Devil": [],
    "Dust_Storm": [],
    "Excessive_Heat": [],
    "Extreme_Cold__FWind_Chill": [],
    "Flash_Flood": [],
    "Flood": [],
    "Freezing_Fog": [],
    "Funnel_Cloud": [],
    "Hail": [],
    "Heat": [],
    "Heavy_Rain": [],
    "Heavy_Snow": [],
    "High_Surf": [],
    "High_Wind": [],
    "Ice_Storm": [],
    "Lakeshore_Flood": [],
    "Landslide": [],
    "Lightning": [],
    "Rip_Current": [],
    "Seiche": [],
    "Sleet": [],
    "Storm_Surge__FTide": [],
    "Strong_Wind": [],
    "Thunderstorm_Wind": [],
    "Tornado": [],
    "Tropical_Depression": [],
    "Tropical_Storm": [],
    "Tsunami": [],
    "Volcanic_Ashfall": [],
    "Waterspout": [],
    "Wildfire": [],
    "Winter_Storm": [],
    "Winter_Weather": []
  },
  "015": {
    "name": "Curry County",
    "fips": "OR",
    "pop10": "22364",
    "lat": 42.466671,
    "lon": -124.211407,
    "geoid": "41015",
    "deaths": 3,
    "prop_dmg": "11.8M",
    "crop_dmg": 0,
    "inj": 1,
    "all": 5,
    "eq": [],
    "Hurricane____Typhoon___": [],
    "Cold__FWind_Chill": [],
    "Coastal_Flood": [],
    "Avalanche": [],
    "Astronomical_Low_Tide": [],
    "Dense_Fog": [],
    "Drought": [],
    "Dust_Devil": [],
    "Dust_Storm": [],
    "Excessive_Heat": [],
    "Extreme_Cold__FWind_Chill": [],
    "Flash_Flood": [],
    "Flood": [
      {
        "type": "Flood",
        "time": "541",
        "inj": "0",
        "deaths": "0",
        "prop_dmg": "4.00M",
        "crop_dmg": "0",
        "begin": "11/29/2012",
        "county": "CURRY CO.",
        "state": "OR"
      }
    ],
    "Freezing_Fog": [],
    "Funnel_Cloud": [],
    "Hail": [],
    "Heat": [],
    "Heavy_Rain": [],
    "Heavy_Snow": [],
    "High_Surf": [
      {
        "type": "High+Surf",
        "time": "1800",
        "inj": "1",
        "deaths": "2",
        "prop_dmg": "0",
        "crop_dmg": "0",
        "begin": "11/10/2005",
        "county": "CURRY COUNTY COAST ",
        "state": "OR"
      },
      {
        "type": "High+Surf",
        "time": "1540",
        "inj": "0",
        "deaths": "1",
        "prop_dmg": "0",
        "crop_dmg": "0",
        "begin": "02/01/2007",
        "county": "CURRY COUNTY COAST ",
        "state": "OR"
      }
    ],
    "High_Wind": [],
    "Ice_Storm": [],
    "Lakeshore_Flood": [],
    "Landslide": [],
    "Lightning": [],
    "Rip_Current": [],
    "Seiche": [],
    "Sleet": [],
    "Storm_Surge__FTide": [
      {
        "type": "Storm+Surge%2FTide",
        "time": "0",
        "inj": "0",
        "deaths": "0",
        "prop_dmg": "300k",
        "crop_dmg": "0",
        "begin": "02/07/1998",
        "county": "CURRY CO.",
        "state": "OR"
      }
    ],
    "Strong_Wind": [],
    "Thunderstorm_Wind": [],
    "Tornado": [],
    "Tropical_Depression": [],
    "Tropical_Storm": [],
    "Tsunami": [
      {
        "type": "Tsunami",
        "time": "711",
        "inj": "0",
        "deaths": "0",
        "prop_dmg": "7.50M",
        "crop_dmg": "0",
        "begin": "03/11/2011",
        "county": "CURRY COUNTY COAST ",
        "state": "OR"
      }
    ],
    "Volcanic_Ashfall": [],
    "Waterspout": [],
    "Wildfire": [],
    "Winter_Storm": [],
    "Winter_Weather": []
  },
  "017": {
    "name": "Deschutes County",
    "fips": "OR",
    "pop10": "157733",
    "lat": 43.915118,
    "lon": -121.225575,
    "geoid": "41017",
    "deaths": 1,
    "prop_dmg": "1.80M",
    "crop_dmg": 0,
    "inj": 3,
    "all": 15,
    "eq": [],
    "Hurricane____Typhoon___": [],
    "Cold__FWind_Chill": [],
    "Coastal_Flood": [],
    "Avalanche": [
      {
        "type": "Avalanche",
        "time": "1415",
        "inj": "1",
        "deaths": "1",
        "prop_dmg": "0",
        "crop_dmg": "0",
        "begin": "03/30/2014",
        "county": "EAST SLOPES OF THE OREGON CASCADES ",
        "state": "OR"
      }
    ],
    "Astronomical_Low_Tide": [],
    "Dense_Fog": [],
    "Drought": [],
    "Dust_Devil": [
      {
        "type": "Dust+Devil",
        "time": "1015",
        "inj": "0",
        "deaths": "0",
        "prop_dmg": "10.0k",
        "crop_dmg": "0",
        "begin": "04/02/2003",
        "county": "DESCHUTES CO.",
        "state": "OR"
      },
      {
        "type": "Dust+Devil",
        "time": "1015",
        "inj": "0",
        "deaths": "0",
        "prop_dmg": "10.0k",
        "crop_dmg": "0",
        "begin": "04/02/2003",
        "county": "DESCHUTES CO.",
        "state": "OR"
      }
    ],
    "Dust_Storm": [],
    "Excessive_Heat": [],
    "Extreme_Cold__FWind_Chill": [],
    "Flash_Flood": [],
    "Flood": [],
    "Freezing_Fog": [],
    "Funnel_Cloud": [],
    "Hail": [],
    "Heat": [],
    "Heavy_Rain": [],
    "Heavy_Snow": [],
    "High_Surf": [],
    "High_Wind": [],
    "Ice_Storm": [],
    "Lakeshore_Flood": [],
    "Landslide": [],
    "Lightning": [
      {
        "type": "Lightning",
        "time": "1745",
        "inj": "0",
        "deaths": "0",
        "prop_dmg": "1.50M",
        "crop_dmg": "0",
        "begin": "06/29/1997",
        "county": "DESCHUTES CO.",
        "state": "OR"
      },
      {
        "type": "Lightning",
        "time": "1700",
        "inj": "0",
        "deaths": "0",
        "prop_dmg": "1.00k",
        "crop_dmg": "0",
        "begin": "07/20/1999",
        "county": "DESCHUTES CO.",
        "state": "OR"
      },
      {
        "type": "Lightning",
        "time": "1700",
        "inj": "0",
        "deaths": "0",
        "prop_dmg": "25.0k",
        "crop_dmg": "0",
        "begin": "08/02/1999",
        "county": "DESCHUTES CO.",
        "state": "OR"
      },
      {
        "type": "Lightning",
        "time": "2000",
        "inj": "0",
        "deaths": "0",
        "prop_dmg": "2.00k",
        "crop_dmg": "0",
        "begin": "05/15/2000",
        "county": "DESCHUTES CO.",
        "state": "OR"
      },
      {
        "type": "Lightning",
        "time": "1700",
        "inj": "0",
        "deaths": "0",
        "prop_dmg": "100k",
        "crop_dmg": "0",
        "begin": "07/19/2001",
        "county": "DESCHUTES CO.",
        "state": "OR"
      },
      {
        "type": "Lightning",
        "time": "2030",
        "inj": "1",
        "deaths": "0",
        "prop_dmg": "1.00k",
        "crop_dmg": "0",
        "begin": "08/04/2004",
        "county": "DESCHUTES CO.",
        "state": "OR"
      },
      {
        "type": "Lightning",
        "time": "1710",
        "inj": "1",
        "deaths": "0",
        "prop_dmg": "0",
        "crop_dmg": "0",
        "begin": "06/03/2009",
        "county": "DESCHUTES CO.",
        "state": "OR"
      },
      {
        "type": "Lightning",
        "time": "1500",
        "inj": "0",
        "deaths": "0",
        "prop_dmg": "50.0k",
        "crop_dmg": "0",
        "begin": "07/27/2010",
        "county": "DESCHUTES CO.",
        "state": "OR"
      },
      {
        "type": "Lightning",
        "time": "1900",
        "inj": "0",
        "deaths": "0",
        "prop_dmg": "5.00k",
        "crop_dmg": "0",
        "begin": "08/05/2012",
        "county": "DESCHUTES CO.",
        "state": "OR"
      },
      {
        "type": "Lightning",
        "time": "1900",
        "inj": "0",
        "deaths": "0",
        "prop_dmg": "100",
        "crop_dmg": "0",
        "begin": "08/05/2012",
        "county": "DESCHUTES CO.",
        "state": "OR"
      },
      {
        "type": "Lightning",
        "time": "1950",
        "inj": "0",
        "deaths": "0",
        "prop_dmg": "20.0k",
        "crop_dmg": "0",
        "begin": "08/05/2012",
        "county": "DESCHUTES CO.",
        "state": "OR"
      },
      {
        "type": "Lightning",
        "time": "1957",
        "inj": "0",
        "deaths": "0",
        "prop_dmg": "75.0k",
        "crop_dmg": "0",
        "begin": "08/05/2012",
        "county": "DESCHUTES CO.",
        "state": "OR"
      }
    ],
    "Rip_Current": [],
    "Seiche": [],
    "Sleet": [],
    "Storm_Surge__FTide": [],
    "Strong_Wind": [],
    "Thunderstorm_Wind": [],
    "Tornado": [],
    "Tropical_Depression": [],
    "Tropical_Storm": [],
    "Tsunami": [],
    "Volcanic_Ashfall": [],
    "Waterspout": [],
    "Wildfire": [],
    "Winter_Storm": [],
    "Winter_Weather": []
  },
  "019": {
    "name": "Douglas County",
    "fips": "OR",
    "pop10": "107667",
    "lat": 43.285904,
    "lon": -123.15438,
    "geoid": "41019",
    "deaths": 0,
    "prop_dmg": 0,
    "crop_dmg": 0,
    "inj": 0,
    "all": 0,
    "eq": [],
    "Hurricane____Typhoon___": [],
    "Cold__FWind_Chill": [],
    "Coastal_Flood": [],
    "Avalanche": [],
    "Astronomical_Low_Tide": [],
    "Dense_Fog": [],
    "Drought": [],
    "Dust_Devil": [],
    "Dust_Storm": [],
    "Excessive_Heat": [],
    "Extreme_Cold__FWind_Chill": [],
    "Flash_Flood": [],
    "Flood": [],
    "Freezing_Fog": [],
    "Funnel_Cloud": [],
    "Hail": [],
    "Heat": [],
    "Heavy_Rain": [],
    "Heavy_Snow": [],
    "High_Surf": [],
    "High_Wind": [],
    "Ice_Storm": [],
    "Lakeshore_Flood": [],
    "Landslide": [],
    "Lightning": [],
    "Rip_Current": [],
    "Seiche": [],
    "Sleet": [],
    "Storm_Surge__FTide": [],
    "Strong_Wind": [],
    "Thunderstorm_Wind": [],
    "Tornado": [],
    "Tropical_Depression": [],
    "Tropical_Storm": [],
    "Tsunami": [],
    "Volcanic_Ashfall": [],
    "Waterspout": [],
    "Wildfire": [],
    "Winter_Storm": [],
    "Winter_Weather": []
  },
  "021": {
    "name": "Gilliam County",
    "fips": "OR",
    "pop10": "1871",
    "lat": 45.381666,
    "lon": -120.211851,
    "geoid": "41021",
    "deaths": 0,
    "prop_dmg": 0,
    "crop_dmg": 0,
    "inj": 0,
    "all": 0,
    "eq": [],
    "Hurricane____Typhoon___": [],
    "Cold__FWind_Chill": [],
    "Coastal_Flood": [],
    "Avalanche": [],
    "Astronomical_Low_Tide": [],
    "Dense_Fog": [],
    "Drought": [],
    "Dust_Devil": [],
    "Dust_Storm": [],
    "Excessive_Heat": [],
    "Extreme_Cold__FWind_Chill": [],
    "Flash_Flood": [],
    "Flood": [],
    "Freezing_Fog": [],
    "Funnel_Cloud": [],
    "Hail": [],
    "Heat": [],
    "Heavy_Rain": [],
    "Heavy_Snow": [],
    "High_Surf": [],
    "High_Wind": [],
    "Ice_Storm": [],
    "Lakeshore_Flood": [],
    "Landslide": [],
    "Lightning": [],
    "Rip_Current": [],
    "Seiche": [],
    "Sleet": [],
    "Storm_Surge__FTide": [],
    "Strong_Wind": [],
    "Thunderstorm_Wind": [],
    "Tornado": [],
    "Tropical_Depression": [],
    "Tropical_Storm": [],
    "Tsunami": [],
    "Volcanic_Ashfall": [],
    "Waterspout": [],
    "Wildfire": [],
    "Winter_Storm": [],
    "Winter_Weather": []
  },
  "023": {
    "name": "Grant County",
    "fips": "OR",
    "pop10": "7445",
    "lat": 44.496326,
    "lon": -119.014057,
    "geoid": "41023",
    "deaths": 0,
    "prop_dmg": 0,
    "crop_dmg": 0,
    "inj": 0,
    "all": 0,
    "eq": [],
    "Hurricane____Typhoon___": [],
    "Cold__FWind_Chill": [],
    "Coastal_Flood": [],
    "Avalanche": [],
    "Astronomical_Low_Tide": [],
    "Dense_Fog": [],
    "Drought": [],
    "Dust_Devil": [],
    "Dust_Storm": [],
    "Excessive_Heat": [],
    "Extreme_Cold__FWind_Chill": [],
    "Flash_Flood": [],
    "Flood": [],
    "Freezing_Fog": [],
    "Funnel_Cloud": [],
    "Hail": [],
    "Heat": [],
    "Heavy_Rain": [],
    "Heavy_Snow": [],
    "High_Surf": [],
    "High_Wind": [],
    "Ice_Storm": [],
    "Lakeshore_Flood": [],
    "Landslide": [],
    "Lightning": [],
    "Rip_Current": [],
    "Seiche": [],
    "Sleet": [],
    "Storm_Surge__FTide": [],
    "Strong_Wind": [],
    "Thunderstorm_Wind": [],
    "Tornado": [],
    "Tropical_Depression": [],
    "Tropical_Storm": [],
    "Tsunami": [],
    "Volcanic_Ashfall": [],
    "Waterspout": [],
    "Wildfire": [],
    "Winter_Storm": [],
    "Winter_Weather": []
  },
  "025": {
    "name": "Harney County",
    "fips": "OR",
    "pop10": "7422",
    "lat": 43.064355,
    "lon": -118.985949,
    "geoid": "41025",
    "deaths": 0,
    "prop_dmg": 0,
    "crop_dmg": 0,
    "inj": 0,
    "all": 0,
    "eq": [],
    "Hurricane____Typhoon___": [],
    "Cold__FWind_Chill": [],
    "Coastal_Flood": [],
    "Avalanche": [],
    "Astronomical_Low_Tide": [],
    "Dense_Fog": [],
    "Drought": [],
    "Dust_Devil": [],
    "Dust_Storm": [],
    "Excessive_Heat": [],
    "Extreme_Cold__FWind_Chill": [],
    "Flash_Flood": [],
    "Flood": [],
    "Freezing_Fog": [],
    "Funnel_Cloud": [],
    "Hail": [],
    "Heat": [],
    "Heavy_Rain": [],
    "Heavy_Snow": [],
    "High_Surf": [],
    "High_Wind": [],
    "Ice_Storm": [],
    "Lakeshore_Flood": [],
    "Landslide": [],
    "Lightning": [],
    "Rip_Current": [],
    "Seiche": [],
    "Sleet": [],
    "Storm_Surge__FTide": [],
    "Strong_Wind": [],
    "Thunderstorm_Wind": [],
    "Tornado": [],
    "Tropical_Depression": [],
    "Tropical_Storm": [],
    "Tsunami": [],
    "Volcanic_Ashfall": [],
    "Waterspout": [],
    "Wildfire": [],
    "Winter_Storm": [],
    "Winter_Weather": []
  },
  "027": {
    "name": "Hood River County",
    "fips": "OR",
    "pop10": "22346",
    "lat": 45.511775,
    "lon": -121.655976,
    "geoid": "41027",
    "deaths": 1,
    "prop_dmg": 0,
    "crop_dmg": 0,
    "inj": 11,
    "all": 4,
    "eq": [],
    "Hurricane____Typhoon___": [],
    "Cold__FWind_Chill": [],
    "Coastal_Flood": [],
    "Avalanche": [
      {
        "type": "Avalanche",
        "time": "1400",
        "inj": "1",
        "deaths": "0",
        "prop_dmg": "0",
        "crop_dmg": "0",
        "begin": "01/15/1998",
        "county": "CENTRAL OREGON ",
        "state": "OR"
      }
    ],
    "Astronomical_Low_Tide": [],
    "Dense_Fog": [],
    "Drought": [],
    "Dust_Devil": [],
    "Dust_Storm": [],
    "Excessive_Heat": [],
    "Extreme_Cold__FWind_Chill": [],
    "Flash_Flood": [],
    "Flood": [],
    "Freezing_Fog": [],
    "Funnel_Cloud": [],
    "Hail": [],
    "Heat": [],
    "Heavy_Rain": [],
    "Heavy_Snow": [
      {
        "type": "Heavy+Snow",
        "time": "900",
        "inj": "4",
        "deaths": "0",
        "prop_dmg": "0",
        "crop_dmg": "0",
        "begin": "01/10/1998",
        "county": "CENTRAL OREGON ",
        "state": "OR"
      }
    ],
    "High_Surf": [],
    "High_Wind": [],
    "Ice_Storm": [
      {
        "type": "Ice+Storm",
        "time": "1600",
        "inj": "5",
        "deaths": "0",
        "prop_dmg": "0",
        "crop_dmg": "0",
        "begin": "01/17/1997",
        "county": "LOWER COLUMBIA BASIN ",
        "state": "OR"
      }
    ],
    "Lakeshore_Flood": [],
    "Landslide": [],
    "Lightning": [],
    "Rip_Current": [],
    "Seiche": [],
    "Sleet": [],
    "Storm_Surge__FTide": [],
    "Strong_Wind": [],
    "Thunderstorm_Wind": [],
    "Tornado": [],
    "Tropical_Depression": [],
    "Tropical_Storm": [],
    "Tsunami": [],
    "Volcanic_Ashfall": [],
    "Waterspout": [],
    "Wildfire": [],
    "Winter_Storm": [
      {
        "type": "Winter+Storm",
        "time": "0",
        "inj": "1",
        "deaths": "1",
        "prop_dmg": "0",
        "crop_dmg": "0",
        "begin": "01/04/1998",
        "county": "LOWER COLUMBIA BASIN ",
        "state": "OR"
      }
    ],
    "Winter_Weather": []
  },
  "029": {
    "name": "Jackson County",
    "fips": "OR",
    "pop10": "203206",
    "lat": 42.411782,
    "lon": -122.675797,
    "geoid": "41029",
    "deaths": 0,
    "prop_dmg": "4.73M",
    "crop_dmg": 0,
    "inj": 2,
    "all": 5,
    "eq": [],
    "Hurricane____Typhoon___": [],
    "Cold__FWind_Chill": [],
    "Coastal_Flood": [],
    "Avalanche": [],
    "Astronomical_Low_Tide": [],
    "Dense_Fog": [
      {
        "type": "Dense+Fog",
        "time": "730",
        "inj": "0",
        "deaths": "0",
        "prop_dmg": "30.0k",
        "crop_dmg": "0",
        "begin": "11/12/2008",
        "county": "JACKSON COUNTY ",
        "state": "OR"
      }
    ],
    "Drought": [],
    "Dust_Devil": [],
    "Dust_Storm": [],
    "Excessive_Heat": [],
    "Extreme_Cold__FWind_Chill": [],
    "Flash_Flood": [],
    "Flood": [],
    "Freezing_Fog": [],
    "Funnel_Cloud": [],
    "Hail": [],
    "Heat": [],
    "Heavy_Rain": [],
    "Heavy_Snow": [],
    "High_Surf": [],
    "High_Wind": [],
    "Ice_Storm": [],
    "Lakeshore_Flood": [],
    "Landslide": [],
    "Lightning": [
      {
        "type": "Lightning",
        "time": "1900",
        "inj": "1",
        "deaths": "0",
        "prop_dmg": "100k",
        "crop_dmg": "0",
        "begin": "05/31/2009",
        "county": "JACKSON CO.",
        "state": "OR"
      },
      {
        "type": "Lightning",
        "time": "1700",
        "inj": "1",
        "deaths": "0",
        "prop_dmg": "0",
        "crop_dmg": "0",
        "begin": "06/02/2009",
        "county": "JACKSON CO.",
        "state": "OR"
      }
    ],
    "Rip_Current": [],
    "Seiche": [],
    "Sleet": [],
    "Storm_Surge__FTide": [],
    "Strong_Wind": [],
    "Thunderstorm_Wind": [],
    "Tornado": [],
    "Tropical_Depression": [],
    "Tropical_Storm": [],
    "Tsunami": [],
    "Volcanic_Ashfall": [],
    "Waterspout": [],
    "Wildfire": [
      {
        "type": "Wildfire",
        "time": "1700",
        "inj": "0",
        "deaths": "0",
        "prop_dmg": "3.10M",
        "crop_dmg": "0",
        "begin": "08/24/2010",
        "county": "JACKSON COUNTY ",
        "state": "OR"
      },
      {
        "type": "Wildfire",
        "time": "0",
        "inj": "0",
        "deaths": "0",
        "prop_dmg": "1.50M",
        "crop_dmg": "0",
        "begin": "08/01/2014",
        "county": "SISKIYOU MOUNTAINS & SOUTHERN OREGON CASCADES ",
        "state": "OR"
      }
    ],
    "Winter_Storm": [],
    "Winter_Weather": []
  },
  "031": {
    "name": "Jefferson County",
    "fips": "OR",
    "pop10": "21720",
    "lat": 44.64379,
    "lon": -121.183021,
    "geoid": "41031",
    "deaths": 1,
    "prop_dmg": "5.54M",
    "crop_dmg": 0,
    "inj": 0,
    "all": 4,
    "eq": [],
    "Hurricane____Typhoon___": [],
    "Cold__FWind_Chill": [],
    "Coastal_Flood": [],
    "Avalanche": [],
    "Astronomical_Low_Tide": [],
    "Dense_Fog": [],
    "Drought": [],
    "Dust_Devil": [],
    "Dust_Storm": [],
    "Excessive_Heat": [],
    "Extreme_Cold__FWind_Chill": [],
    "Flash_Flood": [],
    "Flood": [],
    "Freezing_Fog": [],
    "Funnel_Cloud": [],
    "Hail": [],
    "Heat": [],
    "Heavy_Rain": [],
    "Heavy_Snow": [],
    "High_Surf": [],
    "High_Wind": [],
    "Ice_Storm": [],
    "Lakeshore_Flood": [],
    "Landslide": [],
    "Lightning": [
      {
        "type": "Lightning",
        "time": "1315",
        "inj": "0",
        "deaths": "0",
        "prop_dmg": "40.0k",
        "crop_dmg": "0",
        "begin": "07/19/2004",
        "county": "JEFFERSON CO.",
        "state": "OR"
      },
      {
        "type": "Lightning",
        "time": "1929",
        "inj": "0",
        "deaths": "0",
        "prop_dmg": "500",
        "crop_dmg": "0",
        "begin": "08/05/2012",
        "county": "JEFFERSON CO.",
        "state": "OR"
      },
      {
        "type": "Lightning",
        "time": "1500",
        "inj": "0",
        "deaths": "1",
        "prop_dmg": "0",
        "crop_dmg": "0",
        "begin": "08/25/2013",
        "county": "JEFFERSON CO.",
        "state": "OR"
      }
    ],
    "Rip_Current": [],
    "Seiche": [],
    "Sleet": [],
    "Storm_Surge__FTide": [],
    "Strong_Wind": [],
    "Thunderstorm_Wind": [],
    "Tornado": [],
    "Tropical_Depression": [],
    "Tropical_Storm": [],
    "Tsunami": [],
    "Volcanic_Ashfall": [],
    "Waterspout": [],
    "Wildfire": [
      {
        "type": "Wildfire",
        "time": "0",
        "inj": "0",
        "deaths": "0",
        "prop_dmg": "5.50M",
        "crop_dmg": "0",
        "begin": "07/09/2002",
        "county": "JEFFERSON CO.",
        "state": "OR"
      }
    ],
    "Winter_Storm": [],
    "Winter_Weather": []
  },
  "033": {
    "name": "Josephine County",
    "fips": "OR",
    "pop10": "82713",
    "lat": 42.385382,
    "lon": -123.597245,
    "geoid": "41033",
    "deaths": 0,
    "prop_dmg": "4.06M",
    "crop_dmg": 0,
    "inj": 0,
    "all": 2,
    "eq": [],
    "Hurricane____Typhoon___": [],
    "Cold__FWind_Chill": [],
    "Coastal_Flood": [],
    "Avalanche": [],
    "Astronomical_Low_Tide": [],
    "Dense_Fog": [],
    "Drought": [],
    "Dust_Devil": [],
    "Dust_Storm": [],
    "Excessive_Heat": [],
    "Extreme_Cold__FWind_Chill": [],
    "Flash_Flood": [],
    "Flood": [
      {
        "type": "Flood",
        "time": "541",
        "inj": "0",
        "deaths": "0",
        "prop_dmg": "4.00M",
        "crop_dmg": "0",
        "begin": "11/29/2012",
        "county": "JOSEPHINE CO.",
        "state": "OR"
      }
    ],
    "Freezing_Fog": [],
    "Funnel_Cloud": [],
    "Hail": [],
    "Heat": [],
    "Heavy_Rain": [],
    "Heavy_Snow": [],
    "High_Surf": [],
    "High_Wind": [],
    "Ice_Storm": [],
    "Lakeshore_Flood": [],
    "Landslide": [],
    "Lightning": [
      {
        "type": "Lightning",
        "time": "1200",
        "inj": "0",
        "deaths": "0",
        "prop_dmg": "60.0k",
        "crop_dmg": "0",
        "begin": "07/11/2007",
        "county": "JOSEPHINE CO.",
        "state": "OR"
      }
    ],
    "Rip_Current": [],
    "Seiche": [],
    "Sleet": [],
    "Storm_Surge__FTide": [],
    "Strong_Wind": [],
    "Thunderstorm_Wind": [],
    "Tornado": [],
    "Tropical_Depression": [],
    "Tropical_Storm": [],
    "Tsunami": [],
    "Volcanic_Ashfall": [],
    "Waterspout": [],
    "Wildfire": [],
    "Winter_Storm": [],
    "Winter_Weather": []
  },
  "035": {
    "name": "Klamath County",
    "fips": "OR",
    "pop10": "66380",
    "lat": 42.683761,
    "lon": -121.646168,
    "geoid": "41035",
    "deaths": 0,
    "prop_dmg": 0,
    "crop_dmg": 0,
    "inj": 0,
    "all": 1,
    "eq": [
      {
        "type": "earthquake",
        "begin": "9/21/1993",
        "inj": "",
        "prop_dmg": "",
        "crop_dmg": "",
        "county": "OREGON:  KLAMATH FALLS",
        "state": "OR",
        "deaths": ""
      }
    ],
    "Hurricane____Typhoon___": [],
    "Cold__FWind_Chill": [],
    "Coastal_Flood": [],
    "Avalanche": [],
    "Astronomical_Low_Tide": [],
    "Dense_Fog": [],
    "Drought": [],
    "Dust_Devil": [],
    "Dust_Storm": [],
    "Excessive_Heat": [],
    "Extreme_Cold__FWind_Chill": [],
    "Flash_Flood": [],
    "Flood": [],
    "Freezing_Fog": [],
    "Funnel_Cloud": [],
    "Hail": [],
    "Heat": [],
    "Heavy_Rain": [],
    "Heavy_Snow": [],
    "High_Surf": [],
    "High_Wind": [],
    "Ice_Storm": [],
    "Lakeshore_Flood": [],
    "Landslide": [],
    "Lightning": [],
    "Rip_Current": [],
    "Seiche": [],
    "Sleet": [],
    "Storm_Surge__FTide": [],
    "Strong_Wind": [],
    "Thunderstorm_Wind": [],
    "Tornado": [],
    "Tropical_Depression": [],
    "Tropical_Storm": [],
    "Tsunami": [],
    "Volcanic_Ashfall": [],
    "Waterspout": [],
    "Wildfire": [],
    "Winter_Storm": [],
    "Winter_Weather": []
  },
  "037": {
    "name": "Lake County",
    "fips": "OR",
    "pop10": "7895",
    "lat": 42.788401,
    "lon": -120.38979,
    "geoid": "41037",
    "deaths": 0,
    "prop_dmg": "50.0k",
    "crop_dmg": 0,
    "inj": 0,
    "all": 1,
    "eq": [],
    "Hurricane____Typhoon___": [],
    "Cold__FWind_Chill": [],
    "Coastal_Flood": [],
    "Avalanche": [],
    "Astronomical_Low_Tide": [],
    "Dense_Fog": [],
    "Drought": [],
    "Dust_Devil": [],
    "Dust_Storm": [],
    "Excessive_Heat": [],
    "Extreme_Cold__FWind_Chill": [],
    "Flash_Flood": [],
    "Flood": [],
    "Freezing_Fog": [],
    "Funnel_Cloud": [],
    "Hail": [],
    "Heat": [],
    "Heavy_Rain": [],
    "Heavy_Snow": [],
    "High_Surf": [],
    "High_Wind": [],
    "Ice_Storm": [],
    "Lakeshore_Flood": [],
    "Landslide": [],
    "Lightning": [],
    "Rip_Current": [],
    "Seiche": [],
    "Sleet": [],
    "Storm_Surge__FTide": [],
    "Strong_Wind": [],
    "Thunderstorm_Wind": [],
    "Tornado": [],
    "Tropical_Depression": [],
    "Tropical_Storm": [],
    "Tsunami": [],
    "Volcanic_Ashfall": [],
    "Waterspout": [],
    "Wildfire": [],
    "Winter_Storm": [],
    "Winter_Weather": [
      {
        "type": "Winter+Weather",
        "time": "1130",
        "inj": "0",
        "deaths": "0",
        "prop_dmg": "50.0k",
        "crop_dmg": "0",
        "begin": "01/02/2011",
        "county": "NORTHERN & EASTERN KLAMATH COUNTY & WESTERN LAKE COUNTY ",
        "state": "OR"
      }
    ]
  },
  "039": {
    "name": "Lane County",
    "fips": "OR",
    "pop10": "351715",
    "lat": 43.928276,
    "lon": -122.897678,
    "geoid": "41039",
    "deaths": 0,
    "prop_dmg": "6.40M",
    "crop_dmg": "100k",
    "inj": 4,
    "all": 6,
    "eq": [],
    "Hurricane____Typhoon___": [],
    "Cold__FWind_Chill": [],
    "Coastal_Flood": [],
    "Avalanche": [],
    "Astronomical_Low_Tide": [],
    "Dense_Fog": [],
    "Drought": [],
    "Dust_Devil": [],
    "Dust_Storm": [],
    "Excessive_Heat": [],
    "Extreme_Cold__FWind_Chill": [],
    "Flash_Flood": [],
    "Flood": [
      {
        "type": "Flood",
        "time": "1400",
        "inj": "0",
        "deaths": "0",
        "prop_dmg": "2.00M",
        "crop_dmg": "0",
        "begin": "01/18/2012",
        "county": "LANE CO.",
        "state": "OR"
      },
      {
        "type": "Flood",
        "time": "900",
        "inj": "0",
        "deaths": "0",
        "prop_dmg": "1.00M",
        "crop_dmg": "0",
        "begin": "01/19/2012",
        "county": "LANE CO.",
        "state": "OR"
      }
    ],
    "Freezing_Fog": [],
    "Funnel_Cloud": [],
    "Hail": [],
    "Heat": [],
    "Heavy_Rain": [],
    "Heavy_Snow": [],
    "High_Surf": [],
    "High_Wind": [],
    "Ice_Storm": [],
    "Lakeshore_Flood": [],
    "Landslide": [],
    "Lightning": [],
    "Rip_Current": [],
    "Seiche": [],
    "Sleet": [],
    "Storm_Surge__FTide": [],
    "Strong_Wind": [],
    "Thunderstorm_Wind": [],
    "Tornado": [],
    "Tropical_Depression": [],
    "Tropical_Storm": [],
    "Tsunami": [],
    "Volcanic_Ashfall": [],
    "Waterspout": [],
    "Wildfire": [
      {
        "type": "Wildfire",
        "time": "0",
        "inj": "0",
        "deaths": "0",
        "prop_dmg": "1.70M",
        "crop_dmg": "0",
        "begin": "08/24/1996",
        "county": "LANE CO.",
        "state": "OR"
      },
      {
        "type": "Wildfire",
        "time": "0",
        "inj": "0",
        "deaths": "0",
        "prop_dmg": "1.70M",
        "crop_dmg": "0",
        "begin": "09/01/1996",
        "county": "LANE CO.",
        "state": "OR"
      },
      {
        "type": "Wildfire",
        "time": "1200",
        "inj": "0",
        "deaths": "0",
        "prop_dmg": "0",
        "crop_dmg": "100k",
        "begin": "08/13/1998",
        "county": "LANE CO.",
        "state": "OR"
      },
      {
        "type": "Wildfire",
        "time": "900",
        "inj": "4",
        "deaths": "0",
        "prop_dmg": "0",
        "crop_dmg": "0",
        "begin": "08/17/2002",
        "county": "LANE CO.",
        "state": "OR"
      }
    ],
    "Winter_Storm": [],
    "Winter_Weather": []
  },
  "041": {
    "name": "Lincoln County",
    "fips": "OR",
    "pop10": "46034",
    "lat": 44.641076,
    "lon": -123.911183,
    "geoid": "41041",
    "deaths": 7,
    "prop_dmg": "5.12M",
    "crop_dmg": 0,
    "inj": 5,
    "all": 11,
    "eq": [],
    "Hurricane____Typhoon___": [],
    "Cold__FWind_Chill": [],
    "Coastal_Flood": [],
    "Avalanche": [],
    "Astronomical_Low_Tide": [],
    "Dense_Fog": [],
    "Drought": [],
    "Dust_Devil": [],
    "Dust_Storm": [],
    "Excessive_Heat": [],
    "Extreme_Cold__FWind_Chill": [],
    "Flash_Flood": [],
    "Flood": [
      {
        "type": "Flood",
        "time": "1000",
        "inj": "0",
        "deaths": "0",
        "prop_dmg": "20.0k",
        "crop_dmg": "0",
        "begin": "02/16/1999",
        "county": "LINCOLN/W X LANE ",
        "state": "OR"
      },
      {
        "type": "Flood",
        "time": "1700",
        "inj": "0",
        "deaths": "0",
        "prop_dmg": "3.00M",
        "crop_dmg": "0",
        "begin": "01/18/2012",
        "county": "LINCOLN CO.",
        "state": "OR"
      },
      {
        "type": "Flood",
        "time": "1700",
        "inj": "0",
        "deaths": "0",
        "prop_dmg": "2.00M",
        "crop_dmg": "0",
        "begin": "01/18/2012",
        "county": "LINCOLN CO.",
        "state": "OR"
      }
    ],
    "Freezing_Fog": [],
    "Funnel_Cloud": [],
    "Hail": [],
    "Heat": [],
    "Heavy_Rain": [],
    "Heavy_Snow": [],
    "High_Surf": [
      {
        "type": "High+Surf",
        "time": "2100",
        "inj": "0",
        "deaths": "2",
        "prop_dmg": "0",
        "crop_dmg": "0",
        "begin": "11/18/2009",
        "county": "CENTRAL OREGON COAST ",
        "state": "OR"
      },
      {
        "type": "High+Surf",
        "time": "1730",
        "inj": "1",
        "deaths": "1",
        "prop_dmg": "0",
        "crop_dmg": "0",
        "begin": "04/20/2014",
        "county": "CENTRAL OREGON COAST ",
        "state": "OR"
      }
    ],
    "High_Wind": [],
    "Ice_Storm": [],
    "Lakeshore_Flood": [],
    "Landslide": [],
    "Lightning": [],
    "Rip_Current": [
      {
        "type": "Rip+Current",
        "time": "1630",
        "inj": "0",
        "deaths": "1",
        "prop_dmg": "0",
        "crop_dmg": "0",
        "begin": "03/27/2007",
        "county": "CENTRAL OREGON COAST ",
        "state": "OR"
      },
      {
        "type": "Rip+Current",
        "time": "1300",
        "inj": "0",
        "deaths": "1",
        "prop_dmg": "0",
        "crop_dmg": "0",
        "begin": "03/08/2008",
        "county": "CENTRAL OREGON COAST ",
        "state": "OR"
      },
      {
        "type": "Rip+Current",
        "time": "1300",
        "inj": "0",
        "deaths": "1",
        "prop_dmg": "0",
        "crop_dmg": "0",
        "begin": "03/08/2008",
        "county": "CENTRAL OREGON COAST ",
        "state": "OR"
      },
      {
        "type": "Rip+Current",
        "time": "930",
        "inj": "0",
        "deaths": "1",
        "prop_dmg": "0",
        "crop_dmg": "0",
        "begin": "06/28/2013",
        "county": "CENTRAL OREGON COAST ",
        "state": "OR"
      },
      {
        "type": "Rip+Current",
        "time": "1300",
        "inj": "4",
        "deaths": "0",
        "prop_dmg": "0",
        "crop_dmg": "0",
        "begin": "06/30/2013",
        "county": "CENTRAL OREGON COAST ",
        "state": "OR"
      }
    ],
    "Seiche": [],
    "Sleet": [],
    "Storm_Surge__FTide": [
      {
        "type": "Storm+Surge%2FTide",
        "time": "2000",
        "inj": "0",
        "deaths": "0",
        "prop_dmg": "100k",
        "crop_dmg": "0",
        "begin": "02/03/2006",
        "county": "CENTRAL OREGON COAST ",
        "state": "OR"
      }
    ],
    "Strong_Wind": [],
    "Thunderstorm_Wind": [],
    "Tornado": [],
    "Tropical_Depression": [],
    "Tropical_Storm": [],
    "Tsunami": [],
    "Volcanic_Ashfall": [],
    "Waterspout": [],
    "Wildfire": [],
    "Winter_Storm": [],
    "Winter_Weather": []
  },
  "043": {
    "name": "Linn County",
    "fips": "OR",
    "pop10": "116672",
    "lat": 44.494824,
    "lon": -122.543755,
    "geoid": "41043",
    "deaths": 2,
    "prop_dmg": "61.4M",
    "crop_dmg": "10.5M",
    "inj": 1,
    "all": 5,
    "eq": [],
    "Hurricane____Typhoon___": [],
    "Cold__FWind_Chill": [],
    "Coastal_Flood": [],
    "Avalanche": [],
    "Astronomical_Low_Tide": [],
    "Dense_Fog": [],
    "Drought": [],
    "Dust_Devil": [],
    "Dust_Storm": [],
    "Excessive_Heat": [],
    "Extreme_Cold__FWind_Chill": [],
    "Flash_Flood": [],
    "Flood": [
      {
        "type": "Flood",
        "time": "0",
        "inj": "0",
        "deaths": "0",
        "prop_dmg": "60.4M",
        "crop_dmg": "10.5M",
        "begin": "01/01/1997",
        "county": "ROGUE BASIN ",
        "state": "OR"
      },
      {
        "type": "Flood",
        "time": "1500",
        "inj": "0",
        "deaths": "2",
        "prop_dmg": "0",
        "crop_dmg": "0",
        "begin": "01/18/2012",
        "county": "LINN CO.",
        "state": "OR"
      },
      {
        "type": "Flood",
        "time": "800",
        "inj": "0",
        "deaths": "0",
        "prop_dmg": "1.00M",
        "crop_dmg": "0",
        "begin": "01/19/2012",
        "county": "LINN CO.",
        "state": "OR"
      }
    ],
    "Freezing_Fog": [],
    "Funnel_Cloud": [],
    "Hail": [],
    "Heat": [],
    "Heavy_Rain": [],
    "Heavy_Snow": [],
    "High_Surf": [],
    "High_Wind": [],
    "Ice_Storm": [
      {
        "type": "Ice+Storm",
        "time": "2200",
        "inj": "0",
        "deaths": "0",
        "prop_dmg": "8.00k",
        "crop_dmg": "0",
        "begin": "11/13/2014",
        "county": "SOUTHERN WILLAMETTE VALLEY ",
        "state": "OR"
      }
    ],
    "Lakeshore_Flood": [],
    "Landslide": [],
    "Lightning": [
      {
        "type": "Lightning",
        "time": "1730",
        "inj": "1",
        "deaths": "0",
        "prop_dmg": "0",
        "crop_dmg": "0",
        "begin": "04/25/2003",
        "county": "LINN CO.",
        "state": "OR"
      }
    ],
    "Rip_Current": [],
    "Seiche": [],
    "Sleet": [],
    "Storm_Surge__FTide": [],
    "Strong_Wind": [],
    "Thunderstorm_Wind": [],
    "Tornado": [],
    "Tropical_Depression": [],
    "Tropical_Storm": [],
    "Tsunami": [],
    "Volcanic_Ashfall": [],
    "Waterspout": [],
    "Wildfire": [],
    "Winter_Storm": [],
    "Winter_Weather": []
  },
  "045": {
    "name": "Malheur County",
    "fips": "OR",
    "pop10": "31313",
    "lat": 43.1877,
    "lon": -117.603976,
    "geoid": "41045",
    "deaths": 0,
    "prop_dmg": "10.0k",
    "crop_dmg": 0,
    "inj": 0,
    "all": 1,
    "eq": [],
    "Hurricane____Typhoon___": [],
    "Cold__FWind_Chill": [],
    "Coastal_Flood": [],
    "Avalanche": [],
    "Astronomical_Low_Tide": [],
    "Dense_Fog": [],
    "Drought": [],
    "Dust_Devil": [],
    "Dust_Storm": [],
    "Excessive_Heat": [],
    "Extreme_Cold__FWind_Chill": [],
    "Flash_Flood": [
      {
        "type": "Flash+Flood",
        "time": "1400",
        "inj": "0",
        "deaths": "0",
        "prop_dmg": "10.0k",
        "crop_dmg": "0",
        "begin": "06/12/1998",
        "county": "MALHEUR CO.",
        "state": "OR"
      }
    ],
    "Flood": [],
    "Freezing_Fog": [],
    "Funnel_Cloud": [],
    "Hail": [],
    "Heat": [],
    "Heavy_Rain": [],
    "Heavy_Snow": [],
    "High_Surf": [],
    "High_Wind": [],
    "Ice_Storm": [],
    "Lakeshore_Flood": [],
    "Landslide": [],
    "Lightning": [],
    "Rip_Current": [],
    "Seiche": [],
    "Sleet": [],
    "Storm_Surge__FTide": [],
    "Strong_Wind": [],
    "Thunderstorm_Wind": [],
    "Tornado": [],
    "Tropical_Depression": [],
    "Tropical_Storm": [],
    "Tsunami": [],
    "Volcanic_Ashfall": [],
    "Waterspout": [],
    "Wildfire": [],
    "Winter_Storm": [],
    "Winter_Weather": []
  },
  "047": {
    "name": "Marion County",
    "fips": "OR",
    "pop10": "315335",
    "lat": 44.900898,
    "lon": -122.57626,
    "geoid": "41047",
    "deaths": 0,
    "prop_dmg": "5.39M",
    "crop_dmg": 0,
    "inj": 1,
    "all": 5,
    "eq": [],
    "Hurricane____Typhoon___": [],
    "Cold__FWind_Chill": [],
    "Coastal_Flood": [],
    "Avalanche": [],
    "Astronomical_Low_Tide": [],
    "Dense_Fog": [],
    "Drought": [],
    "Dust_Devil": [],
    "Dust_Storm": [],
    "Excessive_Heat": [],
    "Extreme_Cold__FWind_Chill": [],
    "Flash_Flood": [],
    "Flood": [
      {
        "type": "Flood",
        "time": "1300",
        "inj": "0",
        "deaths": "0",
        "prop_dmg": "1.00M",
        "crop_dmg": "0",
        "begin": "01/20/2012",
        "county": "MARION CO.",
        "state": "OR"
      }
    ],
    "Freezing_Fog": [],
    "Funnel_Cloud": [],
    "Hail": [],
    "Heat": [],
    "Heavy_Rain": [],
    "Heavy_Snow": [],
    "High_Surf": [],
    "High_Wind": [],
    "Ice_Storm": [
      {
        "type": "Ice+Storm",
        "time": "2200",
        "inj": "1",
        "deaths": "0",
        "prop_dmg": "8.00k",
        "crop_dmg": "0",
        "begin": "11/13/2014",
        "county": "CENTRAL WILLAMETTE VALLEY ",
        "state": "OR"
      }
    ],
    "Lakeshore_Flood": [],
    "Landslide": [],
    "Lightning": [
      {
        "type": "Lightning",
        "time": "2200",
        "inj": "0",
        "deaths": "0",
        "prop_dmg": "5.00k",
        "crop_dmg": "0",
        "begin": "07/02/2008",
        "county": "MARION CO.",
        "state": "OR"
      },
      {
        "type": "Lightning",
        "time": "2115",
        "inj": "0",
        "deaths": "0",
        "prop_dmg": "75.0k",
        "crop_dmg": "0",
        "begin": "05/17/2014",
        "county": "MARION CO.",
        "state": "OR"
      }
    ],
    "Rip_Current": [],
    "Seiche": [],
    "Sleet": [],
    "Storm_Surge__FTide": [],
    "Strong_Wind": [],
    "Thunderstorm_Wind": [],
    "Tornado": [],
    "Tropical_Depression": [],
    "Tropical_Storm": [],
    "Tsunami": [],
    "Volcanic_Ashfall": [],
    "Waterspout": [],
    "Wildfire": [
      {
        "type": "Wildfire",
        "time": "1400",
        "inj": "0",
        "deaths": "0",
        "prop_dmg": "4.30M",
        "crop_dmg": "0",
        "begin": "08/12/2001",
        "county": "MARION CO.",
        "state": "OR"
      }
    ],
    "Winter_Storm": [],
    "Winter_Weather": []
  },
  "049": {
    "name": "Morrow County",
    "fips": "OR",
    "pop10": "11173",
    "lat": 45.425496,
    "lon": -119.602311,
    "geoid": "41049",
    "deaths": 1,
    "prop_dmg": "1.56M",
    "crop_dmg": "176k",
    "inj": 9,
    "all": 13,
    "eq": [],
    "Hurricane____Typhoon___": [],
    "Cold__FWind_Chill": [],
    "Coastal_Flood": [],
    "Avalanche": [],
    "Astronomical_Low_Tide": [],
    "Dense_Fog": [
      {
        "type": "Dense+Fog",
        "time": "800",
        "inj": "2",
        "deaths": "0",
        "prop_dmg": "0",
        "crop_dmg": "0",
        "begin": "11/27/2002",
        "county": "LOWER COLUMBIA BASIN ",
        "state": "OR"
      }
    ],
    "Drought": [],
    "Dust_Devil": [],
    "Dust_Storm": [],
    "Excessive_Heat": [],
    "Extreme_Cold__FWind_Chill": [],
    "Flash_Flood": [
      {
        "type": "Flash+Flood",
        "time": "700",
        "inj": "0",
        "deaths": "0",
        "prop_dmg": "70.0k",
        "crop_dmg": "0",
        "begin": "06/02/2011",
        "county": "MORROW CO.",
        "state": "OR"
      }
    ],
    "Flood": [],
    "Freezing_Fog": [],
    "Funnel_Cloud": [],
    "Hail": [],
    "Heat": [],
    "Heavy_Rain": [],
    "Heavy_Snow": [],
    "High_Surf": [],
    "High_Wind": [],
    "Ice_Storm": [],
    "Lakeshore_Flood": [],
    "Landslide": [],
    "Lightning": [
      {
        "type": "Lightning",
        "time": "1800",
        "inj": "1",
        "deaths": "0",
        "prop_dmg": "20.0k",
        "crop_dmg": "0",
        "begin": "08/10/2000",
        "county": "MORROW CO.",
        "state": "OR"
      },
      {
        "type": "Lightning",
        "time": "100",
        "inj": "0",
        "deaths": "0",
        "prop_dmg": "100k",
        "crop_dmg": "20.0k",
        "begin": "08/24/2000",
        "county": "MORROW CO.",
        "state": "OR"
      }
    ],
    "Rip_Current": [],
    "Seiche": [],
    "Sleet": [],
    "Storm_Surge__FTide": [],
    "Strong_Wind": [],
    "Thunderstorm_Wind": [],
    "Tornado": [],
    "Tropical_Depression": [],
    "Tropical_Storm": [],
    "Tsunami": [],
    "Volcanic_Ashfall": [],
    "Waterspout": [],
    "Wildfire": [
      {
        "type": "Wildfire",
        "time": "1030",
        "inj": "0",
        "deaths": "0",
        "prop_dmg": "15.0k",
        "crop_dmg": "500",
        "begin": "11/11/2003",
        "county": "LOWER COLUMBIA BASIN ",
        "state": "OR"
      },
      {
        "type": "Wildfire",
        "time": "1345",
        "inj": "0",
        "deaths": "0",
        "prop_dmg": "18.0k",
        "crop_dmg": "0",
        "begin": "10/18/2004",
        "county": "LOWER COLUMBIA BASIN ",
        "state": "OR"
      },
      {
        "type": "Wildfire",
        "time": "1640",
        "inj": "0",
        "deaths": "0",
        "prop_dmg": "0",
        "crop_dmg": "114k",
        "begin": "06/21/2005",
        "county": "LOWER COLUMBIA BASIN ",
        "state": "OR"
      },
      {
        "type": "Wildfire",
        "time": "1700",
        "inj": "0",
        "deaths": "0",
        "prop_dmg": "10.0k",
        "crop_dmg": "0",
        "begin": "05/18/2006",
        "county": "LOWER COLUMBIA BASIN ",
        "state": "OR"
      },
      {
        "type": "Wildfire",
        "time": "1300",
        "inj": "3",
        "deaths": "0",
        "prop_dmg": "500k",
        "crop_dmg": "0",
        "begin": "06/19/2006",
        "county": "LOWER COLUMBIA BASIN ",
        "state": "OR"
      },
      {
        "type": "Wildfire",
        "time": "1800",
        "inj": "0",
        "deaths": "0",
        "prop_dmg": "10.0k",
        "crop_dmg": "10.0k",
        "begin": "06/29/2008",
        "county": "LOWER COLUMBIA BASIN ",
        "state": "OR"
      },
      {
        "type": "Wildfire",
        "time": "1530",
        "inj": "0",
        "deaths": "0",
        "prop_dmg": "0",
        "crop_dmg": "32.0k",
        "begin": "07/19/2012",
        "county": "LOWER COLUMBIA BASIN ",
        "state": "OR"
      },
      {
        "type": "Wildfire",
        "time": "1300",
        "inj": "0",
        "deaths": "0",
        "prop_dmg": "800k",
        "crop_dmg": "0",
        "begin": "06/11/2013",
        "county": "LOWER COLUMBIA BASIN ",
        "state": "OR"
      }
    ],
    "Winter_Storm": [
      {
        "type": "Winter+Storm",
        "time": "500",
        "inj": "3",
        "deaths": "1",
        "prop_dmg": "15.0k",
        "crop_dmg": "0",
        "begin": "11/24/2000",
        "county": "LOWER COLUMBIA BASIN ",
        "state": "OR"
      }
    ],
    "Winter_Weather": []
  },
  "051": {
    "name": "Multnomah County",
    "fips": "OR",
    "pop10": "735334",
    "lat": 45.547693,
    "lon": -122.417173,
    "geoid": "41051",
    "deaths": 3,
    "prop_dmg": "9.30M",
    "crop_dmg": "2.90M",
    "inj": 0,
    "all": 6,
    "eq": [],
    "Hurricane____Typhoon___": [],
    "Cold__FWind_Chill": [],
    "Coastal_Flood": [],
    "Avalanche": [],
    "Astronomical_Low_Tide": [],
    "Dense_Fog": [],
    "Drought": [],
    "Dust_Devil": [],
    "Dust_Storm": [],
    "Excessive_Heat": [],
    "Extreme_Cold__FWind_Chill": [],
    "Flash_Flood": [],
    "Flood": [
      {
        "type": "Flood",
        "time": "0",
        "inj": "0",
        "deaths": "0",
        "prop_dmg": "9.00M",
        "crop_dmg": "2.90M",
        "begin": "01/01/1997",
        "county": "SOUTH CENTRAL OREGON ",
        "state": "OR"
      }
    ],
    "Freezing_Fog": [],
    "Funnel_Cloud": [],
    "Hail": [],
    "Heat": [],
    "Heavy_Rain": [],
    "Heavy_Snow": [],
    "High_Surf": [],
    "High_Wind": [],
    "Ice_Storm": [],
    "Lakeshore_Flood": [],
    "Landslide": [],
    "Lightning": [
      {
        "type": "Lightning",
        "time": "2000",
        "inj": "0",
        "deaths": "0",
        "prop_dmg": "50.0k",
        "crop_dmg": "0",
        "begin": "06/19/2005",
        "county": "MULTNOMAH CO.",
        "state": "OR"
      },
      {
        "type": "Lightning",
        "time": "100",
        "inj": "0",
        "deaths": "0",
        "prop_dmg": "2.00k",
        "crop_dmg": "0",
        "begin": "07/03/2008",
        "county": "MULTNOMAH CO.",
        "state": "OR"
      }
    ],
    "Rip_Current": [],
    "Seiche": [],
    "Sleet": [],
    "Storm_Surge__FTide": [],
    "Strong_Wind": [],
    "Thunderstorm_Wind": [],
    "Tornado": [
      {
        "type": "Tornado",
        "time": "1450",
        "inj": "0",
        "deaths": "0",
        "prop_dmg": "250k",
        "crop_dmg": "0",
        "begin": "04/05/1972",
        "county": "MULTNOMAH CO.",
        "state": "OR"
      }
    ],
    "Tropical_Depression": [],
    "Tropical_Storm": [],
    "Tsunami": [],
    "Volcanic_Ashfall": [],
    "Waterspout": [],
    "Wildfire": [],
    "Winter_Storm": [
      {
        "type": "Winter+Storm",
        "time": "900",
        "inj": "0",
        "deaths": "2",
        "prop_dmg": "0",
        "crop_dmg": "0",
        "begin": "01/02/1998",
        "county": "SOUTH CENTRAL OREGON ",
        "state": "OR"
      },
      {
        "type": "Winter+Storm",
        "time": "1200",
        "inj": "0",
        "deaths": "1",
        "prop_dmg": "0",
        "crop_dmg": "0",
        "begin": "01/01/1998",
        "county": "LAKE/KLAMATH T X W ",
        "state": "OR"
      }
    ],
    "Winter_Weather": []
  },
  "053": {
    "name": "Polk County",
    "fips": "OR",
    "pop10": "75403",
    "lat": 44.904395,
    "lon": -123.397329,
    "geoid": "41053",
    "deaths": 0,
    "prop_dmg": "3.00M",
    "crop_dmg": 0,
    "inj": 0,
    "all": 1,
    "eq": [],
    "Hurricane____Typhoon___": [],
    "Cold__FWind_Chill": [],
    "Coastal_Flood": [],
    "Avalanche": [],
    "Astronomical_Low_Tide": [],
    "Dense_Fog": [],
    "Drought": [],
    "Dust_Devil": [],
    "Dust_Storm": [],
    "Excessive_Heat": [],
    "Extreme_Cold__FWind_Chill": [],
    "Flash_Flood": [],
    "Flood": [
      {
        "type": "Flood",
        "time": "2200",
        "inj": "0",
        "deaths": "0",
        "prop_dmg": "3.00M",
        "crop_dmg": "0",
        "begin": "01/18/2012",
        "county": "POLK CO.",
        "state": "OR"
      }
    ],
    "Freezing_Fog": [],
    "Funnel_Cloud": [],
    "Hail": [],
    "Heat": [],
    "Heavy_Rain": [],
    "Heavy_Snow": [],
    "High_Surf": [],
    "High_Wind": [],
    "Ice_Storm": [],
    "Lakeshore_Flood": [],
    "Landslide": [],
    "Lightning": [],
    "Rip_Current": [],
    "Seiche": [],
    "Sleet": [],
    "Storm_Surge__FTide": [],
    "Strong_Wind": [],
    "Thunderstorm_Wind": [],
    "Tornado": [],
    "Tropical_Depression": [],
    "Tropical_Storm": [],
    "Tsunami": [],
    "Volcanic_Ashfall": [],
    "Waterspout": [],
    "Wildfire": [],
    "Winter_Storm": [],
    "Winter_Weather": []
  },
  "055": {
    "name": "Sherman County",
    "fips": "OR",
    "pop10": "1765",
    "lat": 45.399216,
    "lon": -120.678512,
    "geoid": "41055",
    "deaths": 0,
    "prop_dmg": 0,
    "crop_dmg": 0,
    "inj": 0,
    "all": 0,
    "eq": [],
    "Hurricane____Typhoon___": [],
    "Cold__FWind_Chill": [],
    "Coastal_Flood": [],
    "Avalanche": [],
    "Astronomical_Low_Tide": [],
    "Dense_Fog": [],
    "Drought": [],
    "Dust_Devil": [],
    "Dust_Storm": [],
    "Excessive_Heat": [],
    "Extreme_Cold__FWind_Chill": [],
    "Flash_Flood": [],
    "Flood": [],
    "Freezing_Fog": [],
    "Funnel_Cloud": [],
    "Hail": [],
    "Heat": [],
    "Heavy_Rain": [],
    "Heavy_Snow": [],
    "High_Surf": [],
    "High_Wind": [],
    "Ice_Storm": [],
    "Lakeshore_Flood": [],
    "Landslide": [],
    "Lightning": [],
    "Rip_Current": [],
    "Seiche": [],
    "Sleet": [],
    "Storm_Surge__FTide": [],
    "Strong_Wind": [],
    "Thunderstorm_Wind": [],
    "Tornado": [],
    "Tropical_Depression": [],
    "Tropical_Storm": [],
    "Tsunami": [],
    "Volcanic_Ashfall": [],
    "Waterspout": [],
    "Wildfire": [],
    "Winter_Storm": [],
    "Winter_Weather": []
  },
  "057": {
    "name": "Tillamook County",
    "fips": "OR",
    "pop10": "25250",
    "lat": 45.455743,
    "lon": -123.759327,
    "geoid": "41057",
    "deaths": 7,
    "prop_dmg": "8.00M",
    "crop_dmg": 0,
    "inj": 7,
    "all": 13,
    "eq": [],
    "Hurricane____Typhoon___": [],
    "Cold__FWind_Chill": [],
    "Coastal_Flood": [],
    "Avalanche": [],
    "Astronomical_Low_Tide": [],
    "Dense_Fog": [],
    "Drought": [],
    "Dust_Devil": [],
    "Dust_Storm": [],
    "Excessive_Heat": [],
    "Extreme_Cold__FWind_Chill": [],
    "Flash_Flood": [],
    "Flood": [
      {
        "type": "Flood",
        "time": "0",
        "inj": "0",
        "deaths": "0",
        "prop_dmg": "7.20M",
        "crop_dmg": "0",
        "begin": "01/01/1997",
        "county": "SOUTHERN COAST ",
        "state": "OR"
      },
      {
        "type": "Flood",
        "time": "1000",
        "inj": "0",
        "deaths": "0",
        "prop_dmg": "80.0k",
        "crop_dmg": "0",
        "begin": "02/16/1999",
        "county": "CLATSOP/TILLAMOOK ",
        "state": "OR"
      }
    ],
    "Freezing_Fog": [],
    "Funnel_Cloud": [],
    "Hail": [],
    "Heat": [],
    "Heavy_Rain": [],
    "Heavy_Snow": [],
    "High_Surf": [
      {
        "type": "High+Surf",
        "time": "615",
        "inj": "0",
        "deaths": "0",
        "prop_dmg": "500k",
        "crop_dmg": "0",
        "begin": "06/14/2003",
        "county": "NORTHERN OREGON COAST ",
        "state": "OR"
      },
      {
        "type": "High+Surf",
        "time": "1300",
        "inj": "1",
        "deaths": "1",
        "prop_dmg": "0",
        "crop_dmg": "0",
        "begin": "04/24/2014",
        "county": "NORTHERN OREGON COAST ",
        "state": "OR"
      },
      {
        "type": "High+Surf",
        "time": "1600",
        "inj": "1",
        "deaths": "1",
        "prop_dmg": "0",
        "crop_dmg": "0",
        "begin": "08/04/2014",
        "county": "NORTHERN OREGON COAST ",
        "state": "OR"
      }
    ],
    "High_Wind": [],
    "Ice_Storm": [
      {
        "type": "Ice+Storm",
        "time": "1300",
        "inj": "0",
        "deaths": "1",
        "prop_dmg": "0",
        "crop_dmg": "0",
        "begin": "02/03/1996",
        "county": "NORTHERN OREGON COAST ",
        "state": "OR"
      },
      {
        "type": "Ice+Storm",
        "time": "400",
        "inj": "0",
        "deaths": "0",
        "prop_dmg": "50.0k",
        "crop_dmg": "0",
        "begin": "01/11/1998",
        "county": "CLATSOP/TILLAMOOK ",
        "state": "OR"
      }
    ],
    "Lakeshore_Flood": [],
    "Landslide": [],
    "Lightning": [
      {
        "type": "Lightning",
        "time": "2030",
        "inj": "0",
        "deaths": "0",
        "prop_dmg": "15.0k",
        "crop_dmg": "0",
        "begin": "01/17/1999",
        "county": "TILLAMOOK CO.",
        "state": "OR"
      }
    ],
    "Rip_Current": [
      {
        "type": "Rip+Current",
        "time": "2000",
        "inj": "2",
        "deaths": "1",
        "prop_dmg": "0",
        "crop_dmg": "0",
        "begin": "07/03/2007",
        "county": "NORTHERN OREGON COAST ",
        "state": "OR"
      },
      {
        "type": "Rip+Current",
        "time": "2000",
        "inj": "2",
        "deaths": "1",
        "prop_dmg": "0",
        "crop_dmg": "0",
        "begin": "07/03/2007",
        "county": "NORTHERN OREGON COAST ",
        "state": "OR"
      },
      {
        "type": "Rip+Current",
        "time": "1720",
        "inj": "1",
        "deaths": "1",
        "prop_dmg": "0",
        "crop_dmg": "0",
        "begin": "07/22/2014",
        "county": "NORTHERN OREGON COAST ",
        "state": "OR"
      }
    ],
    "Seiche": [],
    "Sleet": [],
    "Storm_Surge__FTide": [
      {
        "type": "Storm+Surge%2FTide",
        "time": "2000",
        "inj": "0",
        "deaths": "0",
        "prop_dmg": "100k",
        "crop_dmg": "0",
        "begin": "02/03/2006",
        "county": "NORTHERN OREGON COAST ",
        "state": "OR"
      }
    ],
    "Strong_Wind": [],
    "Thunderstorm_Wind": [],
    "Tornado": [],
    "Tropical_Depression": [],
    "Tropical_Storm": [],
    "Tsunami": [],
    "Volcanic_Ashfall": [],
    "Waterspout": [],
    "Wildfire": [],
    "Winter_Storm": [
      {
        "type": "Winter+Storm",
        "time": "200",
        "inj": "0",
        "deaths": "1",
        "prop_dmg": "50.0k",
        "crop_dmg": "0",
        "begin": "01/11/1998",
        "county": "CLATSOP/TILLAMOOK ",
        "state": "OR"
      }
    ],
    "Winter_Weather": []
  },
  "059": {
    "name": "Umatilla County",
    "fips": "OR",
    "pop10": "75889",
    "lat": 45.5912,
    "lon": -118.73388,
    "geoid": "41059",
    "deaths": 0,
    "prop_dmg": "249k",
    "crop_dmg": "7.20M",
    "inj": 0,
    "all": 10,
    "eq": [],
    "Hurricane____Typhoon___": [],
    "Cold__FWind_Chill": [],
    "Coastal_Flood": [],
    "Avalanche": [],
    "Astronomical_Low_Tide": [],
    "Dense_Fog": [],
    "Drought": [],
    "Dust_Devil": [],
    "Dust_Storm": [],
    "Excessive_Heat": [],
    "Extreme_Cold__FWind_Chill": [],
    "Flash_Flood": [
      {
        "type": "Flash+Flood",
        "time": "200",
        "inj": "0",
        "deaths": "0",
        "prop_dmg": "100k",
        "crop_dmg": "0",
        "begin": "07/16/2012",
        "county": "UMATILLA CO.",
        "state": "OR"
      },
      {
        "type": "Flash+Flood",
        "time": "200",
        "inj": "0",
        "deaths": "0",
        "prop_dmg": "100k",
        "crop_dmg": "0",
        "begin": "07/16/2012",
        "county": "UMATILLA CO.",
        "state": "OR"
      }
    ],
    "Flood": [],
    "Freezing_Fog": [],
    "Funnel_Cloud": [],
    "Hail": [],
    "Heat": [],
    "Heavy_Rain": [
      {
        "type": "Heavy+Rain",
        "time": "0",
        "inj": "0",
        "deaths": "0",
        "prop_dmg": "4.00k",
        "crop_dmg": "0",
        "begin": "02/14/2000",
        "county": "UMATILLA CO.",
        "state": "OR"
      },
      {
        "type": "Heavy+Rain",
        "time": "0",
        "inj": "0",
        "deaths": "0",
        "prop_dmg": "0",
        "crop_dmg": "3.50M",
        "begin": "06/01/2010",
        "county": "UMATILLA CO.",
        "state": "OR"
      },
      {
        "type": "Heavy+Rain",
        "time": "0",
        "inj": "0",
        "deaths": "0",
        "prop_dmg": "0",
        "crop_dmg": "3.50M",
        "begin": "06/01/2010",
        "county": "UMATILLA CO.",
        "state": "OR"
      }
    ],
    "Heavy_Snow": [],
    "High_Surf": [],
    "High_Wind": [],
    "Ice_Storm": [],
    "Lakeshore_Flood": [],
    "Landslide": [],
    "Lightning": [
      {
        "type": "Lightning",
        "time": "1445",
        "inj": "0",
        "deaths": "0",
        "prop_dmg": "1.00k",
        "crop_dmg": "0",
        "begin": "08/02/2004",
        "county": "UMATILLA CO.",
        "state": "OR"
      },
      {
        "type": "Lightning",
        "time": "1750",
        "inj": "0",
        "deaths": "0",
        "prop_dmg": "1.00k",
        "crop_dmg": "0",
        "begin": "06/12/2006",
        "county": "UMATILLA CO.",
        "state": "OR"
      },
      {
        "type": "Lightning",
        "time": "1630",
        "inj": "0",
        "deaths": "0",
        "prop_dmg": "2.00k",
        "crop_dmg": "0",
        "begin": "04/21/2011",
        "county": "UMATILLA CO.",
        "state": "OR"
      },
      {
        "type": "Lightning",
        "time": "1657",
        "inj": "0",
        "deaths": "0",
        "prop_dmg": "500",
        "crop_dmg": "0",
        "begin": "05/14/2011",
        "county": "UMATILLA CO.",
        "state": "OR"
      }
    ],
    "Rip_Current": [],
    "Seiche": [],
    "Sleet": [],
    "Storm_Surge__FTide": [],
    "Strong_Wind": [],
    "Thunderstorm_Wind": [],
    "Tornado": [],
    "Tropical_Depression": [],
    "Tropical_Storm": [],
    "Tsunami": [],
    "Volcanic_Ashfall": [],
    "Waterspout": [],
    "Wildfire": [
      {
        "type": "Wildfire",
        "time": "1200",
        "inj": "0",
        "deaths": "0",
        "prop_dmg": "40.0k",
        "crop_dmg": "200k",
        "begin": "10/28/2003",
        "county": "UMATILLA CO.",
        "state": "OR"
      }
    ],
    "Winter_Storm": [],
    "Winter_Weather": []
  },
  "061": {
    "name": "Union County",
    "fips": "OR",
    "pop10": "25748",
    "lat": 45.304047,
    "lon": -117.999136,
    "geoid": "41061",
    "deaths": 1,
    "prop_dmg": "119k",
    "crop_dmg": 0,
    "inj": 0,
    "all": 5,
    "eq": [],
    "Hurricane____Typhoon___": [],
    "Cold__FWind_Chill": [
      {
        "type": "Cold%2FWind+Chill",
        "time": "2000",
        "inj": "0",
        "deaths": "1",
        "prop_dmg": "0",
        "crop_dmg": "0",
        "begin": "01/05/2004",
        "county": "GRAND RONDE VALLEY ",
        "state": "OR"
      }
    ],
    "Coastal_Flood": [],
    "Avalanche": [],
    "Astronomical_Low_Tide": [],
    "Dense_Fog": [],
    "Drought": [],
    "Dust_Devil": [],
    "Dust_Storm": [],
    "Excessive_Heat": [],
    "Extreme_Cold__FWind_Chill": [],
    "Flash_Flood": [],
    "Flood": [],
    "Freezing_Fog": [
      {
        "type": "Freezing+Fog",
        "time": "700",
        "inj": "0",
        "deaths": "0",
        "prop_dmg": "50.0k",
        "crop_dmg": "0",
        "begin": "02/27/2012",
        "county": "NORTHERN BLUE MOUNTAINS ",
        "state": "OR"
      }
    ],
    "Funnel_Cloud": [],
    "Hail": [],
    "Heat": [],
    "Heavy_Rain": [],
    "Heavy_Snow": [],
    "High_Surf": [],
    "High_Wind": [],
    "Ice_Storm": [],
    "Lakeshore_Flood": [],
    "Landslide": [],
    "Lightning": [
      {
        "type": "Lightning",
        "time": "945",
        "inj": "0",
        "deaths": "0",
        "prop_dmg": "46.0k",
        "crop_dmg": "0",
        "begin": "08/13/1999",
        "county": "UNION CO.",
        "state": "OR"
      },
      {
        "type": "Lightning",
        "time": "1155",
        "inj": "0",
        "deaths": "0",
        "prop_dmg": "3.00k",
        "crop_dmg": "0",
        "begin": "05/11/2000",
        "county": "UNION CO.",
        "state": "OR"
      },
      {
        "type": "Lightning",
        "time": "1300",
        "inj": "0",
        "deaths": "0",
        "prop_dmg": "20.0k",
        "crop_dmg": "0",
        "begin": "08/04/2001",
        "county": "UNION CO.",
        "state": "OR"
      }
    ],
    "Rip_Current": [],
    "Seiche": [],
    "Sleet": [],
    "Storm_Surge__FTide": [],
    "Strong_Wind": [],
    "Thunderstorm_Wind": [],
    "Tornado": [],
    "Tropical_Depression": [],
    "Tropical_Storm": [],
    "Tsunami": [],
    "Volcanic_Ashfall": [],
    "Waterspout": [],
    "Wildfire": [],
    "Winter_Storm": [],
    "Winter_Weather": []
  },
  "063": {
    "name": "Wallowa County",
    "fips": "OR",
    "pop10": "7008",
    "lat": 45.593753,
    "lon": -117.18558,
    "geoid": "41063",
    "deaths": 1,
    "prop_dmg": "25.0M",
    "crop_dmg": 0,
    "inj": 2,
    "all": 3,
    "eq": [],
    "Hurricane____Typhoon___": [],
    "Cold__FWind_Chill": [],
    "Coastal_Flood": [],
    "Avalanche": [
      {
        "type": "Avalanche",
        "time": "1300",
        "inj": "2",
        "deaths": "1",
        "prop_dmg": "0",
        "crop_dmg": "0",
        "begin": "03/07/2009",
        "county": "WALLOWA COUNTY ",
        "state": "OR"
      }
    ],
    "Astronomical_Low_Tide": [],
    "Dense_Fog": [],
    "Drought": [],
    "Dust_Devil": [],
    "Dust_Storm": [],
    "Excessive_Heat": [],
    "Extreme_Cold__FWind_Chill": [],
    "Flash_Flood": [],
    "Flood": [],
    "Freezing_Fog": [],
    "Funnel_Cloud": [],
    "Hail": [],
    "Heat": [],
    "Heavy_Rain": [],
    "Heavy_Snow": [],
    "High_Surf": [],
    "High_Wind": [],
    "Ice_Storm": [],
    "Lakeshore_Flood": [],
    "Landslide": [],
    "Lightning": [
      {
        "type": "Lightning",
        "time": "1730",
        "inj": "0",
        "deaths": "0",
        "prop_dmg": "40.0k",
        "crop_dmg": "0",
        "begin": "05/24/2001",
        "county": "WALLOWA CO.",
        "state": "OR"
      }
    ],
    "Rip_Current": [],
    "Seiche": [],
    "Sleet": [],
    "Storm_Surge__FTide": [],
    "Strong_Wind": [],
    "Thunderstorm_Wind": [],
    "Tornado": [
      {
        "type": "Tornado",
        "time": "1800",
        "inj": "0",
        "deaths": "0",
        "prop_dmg": "25.0M",
        "crop_dmg": "0",
        "begin": "06/11/1968",
        "county": "WALLOWA CO.",
        "state": "OR"
      }
    ],
    "Tropical_Depression": [],
    "Tropical_Storm": [],
    "Tsunami": [],
    "Volcanic_Ashfall": [],
    "Waterspout": [],
    "Wildfire": [],
    "Winter_Storm": [],
    "Winter_Weather": []
  },
  "065": {
    "name": "Wasco County",
    "fips": "OR",
    "pop10": "25213",
    "lat": 45.164536,
    "lon": -121.165069,
    "geoid": "41065",
    "deaths": 0,
    "prop_dmg": "10.0k",
    "crop_dmg": 0,
    "inj": 0,
    "all": 1,
    "eq": [],
    "Hurricane____Typhoon___": [],
    "Cold__FWind_Chill": [],
    "Coastal_Flood": [],
    "Avalanche": [],
    "Astronomical_Low_Tide": [],
    "Dense_Fog": [],
    "Drought": [],
    "Dust_Devil": [],
    "Dust_Storm": [],
    "Excessive_Heat": [],
    "Extreme_Cold__FWind_Chill": [],
    "Flash_Flood": [],
    "Flood": [],
    "Freezing_Fog": [],
    "Funnel_Cloud": [],
    "Hail": [],
    "Heat": [],
    "Heavy_Rain": [],
    "Heavy_Snow": [],
    "High_Surf": [],
    "High_Wind": [],
    "Ice_Storm": [],
    "Lakeshore_Flood": [],
    "Landslide": [],
    "Lightning": [],
    "Rip_Current": [],
    "Seiche": [],
    "Sleet": [],
    "Storm_Surge__FTide": [],
    "Strong_Wind": [],
    "Thunderstorm_Wind": [],
    "Tornado": [],
    "Tropical_Depression": [],
    "Tropical_Storm": [],
    "Tsunami": [],
    "Volcanic_Ashfall": [],
    "Waterspout": [],
    "Wildfire": [
      {
        "type": "Wildfire",
        "time": "0",
        "inj": "0",
        "deaths": "0",
        "prop_dmg": "10.0k",
        "crop_dmg": "0",
        "begin": "07/23/2002",
        "county": "WASCO CO.",
        "state": "OR"
      }
    ],
    "Winter_Storm": [],
    "Winter_Weather": []
  },
  "067": {
    "name": "Washington County",
    "fips": "OR",
    "pop10": "529710",
    "lat": 45.553542,
    "lon": -123.097615,
    "geoid": "41067",
    "deaths": 0,
    "prop_dmg": "423k",
    "crop_dmg": 0,
    "inj": 0,
    "all": 5,
    "eq": [],
    "Hurricane____Typhoon___": [],
    "Cold__FWind_Chill": [],
    "Coastal_Flood": [],
    "Avalanche": [],
    "Astronomical_Low_Tide": [],
    "Dense_Fog": [],
    "Drought": [],
    "Dust_Devil": [],
    "Dust_Storm": [],
    "Excessive_Heat": [],
    "Extreme_Cold__FWind_Chill": [],
    "Flash_Flood": [],
    "Flood": [],
    "Freezing_Fog": [],
    "Funnel_Cloud": [],
    "Hail": [],
    "Heat": [],
    "Heavy_Rain": [
      {
        "type": "Heavy+Rain",
        "time": "1825",
        "inj": "0",
        "deaths": "0",
        "prop_dmg": "140k",
        "crop_dmg": "0",
        "begin": "06/25/2014",
        "county": "WASHINGTON CO.",
        "state": "OR"
      }
    ],
    "Heavy_Snow": [],
    "High_Surf": [],
    "High_Wind": [],
    "Ice_Storm": [],
    "Lakeshore_Flood": [],
    "Landslide": [],
    "Lightning": [
      {
        "type": "Lightning",
        "time": "1440",
        "inj": "0",
        "deaths": "0",
        "prop_dmg": "150k",
        "crop_dmg": "0",
        "begin": "08/05/2003",
        "county": "WASHINGTON CO.",
        "state": "OR"
      },
      {
        "type": "Lightning",
        "time": "220",
        "inj": "0",
        "deaths": "0",
        "prop_dmg": "5.00k",
        "crop_dmg": "0",
        "begin": "07/02/2008",
        "county": "WASHINGTON CO.",
        "state": "OR"
      },
      {
        "type": "Lightning",
        "time": "1300",
        "inj": "0",
        "deaths": "0",
        "prop_dmg": "28.0k",
        "crop_dmg": "0",
        "begin": "09/15/2013",
        "county": "WASHINGTON CO.",
        "state": "OR"
      }
    ],
    "Rip_Current": [],
    "Seiche": [],
    "Sleet": [],
    "Storm_Surge__FTide": [],
    "Strong_Wind": [],
    "Thunderstorm_Wind": [],
    "Tornado": [],
    "Tropical_Depression": [],
    "Tropical_Storm": [],
    "Tsunami": [],
    "Volcanic_Ashfall": [],
    "Waterspout": [],
    "Wildfire": [],
    "Winter_Storm": [
      {
        "type": "Winter+Storm",
        "time": "600",
        "inj": "0",
        "deaths": "0",
        "prop_dmg": "100k",
        "crop_dmg": "0",
        "begin": "01/11/1998",
        "county": "BENTON/W & C LINN/C LANE ",
        "state": "OR"
      }
    ],
    "Winter_Weather": []
  },
  "069": {
    "name": "Wheeler County",
    "fips": "OR",
    "pop10": "1441",
    "lat": 44.736411,
    "lon": -120.026875,
    "geoid": "41069",
    "deaths": 1,
    "prop_dmg": "11.0k",
    "crop_dmg": 0,
    "inj": 0,
    "all": 3,
    "eq": [],
    "Hurricane____Typhoon___": [],
    "Cold__FWind_Chill": [],
    "Coastal_Flood": [],
    "Avalanche": [],
    "Astronomical_Low_Tide": [],
    "Dense_Fog": [],
    "Drought": [],
    "Dust_Devil": [],
    "Dust_Storm": [],
    "Excessive_Heat": [],
    "Extreme_Cold__FWind_Chill": [],
    "Flash_Flood": [
      {
        "type": "Flash+Flood",
        "time": "1930",
        "inj": "0",
        "deaths": "0",
        "prop_dmg": "5.00k",
        "crop_dmg": "0",
        "begin": "04/26/2001",
        "county": "WHEELER CO.",
        "state": "OR"
      },
      {
        "type": "Flash+Flood",
        "time": "1820",
        "inj": "0",
        "deaths": "0",
        "prop_dmg": "6.00k",
        "crop_dmg": "0",
        "begin": "06/04/2007",
        "county": "WHEELER CO.",
        "state": "OR"
      }
    ],
    "Flood": [],
    "Freezing_Fog": [],
    "Funnel_Cloud": [],
    "Hail": [],
    "Heat": [],
    "Heavy_Rain": [],
    "Heavy_Snow": [],
    "High_Surf": [],
    "High_Wind": [],
    "Ice_Storm": [],
    "Lakeshore_Flood": [],
    "Landslide": [],
    "Lightning": [
      {
        "type": "Lightning",
        "time": "1730",
        "inj": "0",
        "deaths": "1",
        "prop_dmg": "0",
        "crop_dmg": "0",
        "begin": "05/14/1997",
        "county": "WHEELER CO.",
        "state": "OR"
      }
    ],
    "Rip_Current": [],
    "Seiche": [],
    "Sleet": [],
    "Storm_Surge__FTide": [],
    "Strong_Wind": [],
    "Thunderstorm_Wind": [],
    "Tornado": [],
    "Tropical_Depression": [],
    "Tropical_Storm": [],
    "Tsunami": [],
    "Volcanic_Ashfall": [],
    "Waterspout": [],
    "Wildfire": [],
    "Winter_Storm": [],
    "Winter_Weather": []
  },
  "071": {
    "name": "Yamhill County",
    "fips": "OR",
    "pop10": "99193",
    "lat": 45.248138,
    "lon": -123.316117,
    "geoid": "41071",
    "deaths": 0,
    "prop_dmg": "2.00M",
    "crop_dmg": 0,
    "inj": 0,
    "all": 1,
    "eq": [],
    "Hurricane____Typhoon___": [],
    "Cold__FWind_Chill": [],
    "Coastal_Flood": [],
    "Avalanche": [],
    "Astronomical_Low_Tide": [],
    "Dense_Fog": [],
    "Drought": [],
    "Dust_Devil": [],
    "Dust_Storm": [],
    "Excessive_Heat": [],
    "Extreme_Cold__FWind_Chill": [],
    "Flash_Flood": [],
    "Flood": [
      {
        "type": "Flood",
        "time": "500",
        "inj": "0",
        "deaths": "0",
        "prop_dmg": "2.00M",
        "crop_dmg": "0",
        "begin": "01/20/2012",
        "county": "YAMHILL CO.",
        "state": "OR"
      }
    ],
    "Freezing_Fog": [],
    "Funnel_Cloud": [],
    "Hail": [],
    "Heat": [],
    "Heavy_Rain": [],
    "Heavy_Snow": [],
    "High_Surf": [],
    "High_Wind": [],
    "Ice_Storm": [],
    "Lakeshore_Flood": [],
    "Landslide": [],
    "Lightning": [],
    "Rip_Current": [],
    "Seiche": [],
    "Sleet": [],
    "Storm_Surge__FTide": [],
    "Strong_Wind": [],
    "Thunderstorm_Wind": [],
    "Tornado": [],
    "Tropical_Depression": [],
    "Tropical_Storm": [],
    "Tsunami": [],
    "Volcanic_Ashfall": [],
    "Waterspout": [],
    "Wildfire": [],
    "Winter_Storm": [],
    "Winter_Weather": []
  }
}